Base/CustomRequest.py
Base/NSEBase.py
Base/__init__.py
Derivatives/NSE.py
Derivatives/Sensibull.py
Derivatives/__init__.py
Fundamentals/BSE.py
Fundamentals/MoneyControl.py
Fundamentals/Screener.py
Fundamentals/TickerTape.py
Fundamentals/__init__.py
Technical/NSE.py
Technical/__init__.py
bharat_sm_data_avinash-4.1.0.dist-info/licenses/LICENSE
bharat_sm_data_avinash-4.1.0.dist-info/METADATA
bharat_sm_data_avinash-4.1.0.dist-info/WHEEL
bharat_sm_data_avinash-4.1.0.dist-info/top_level.txt
bharat_sm_data_avinash-4.1.0.dist-info/RECORD
